setup.py
podcast/__init__.py
podcast.egg-info/PKG-INFO
podcast.egg-info/SOURCES.txt
podcast.egg-info/dependency_links.txt
podcast.egg-info/top_level.txt